README.md
setup.py
stromer_api/__init__.py
stromer_api/bikedata.py
stromer_api/bikemaintenance.py
stromer_api/bikemotortuning.py
stromer_api/bikepart.py
stromer_api/bikeposition.py
stromer_api/bikesensors.py
stromer_api/bikesettings.py
stromer_api/bikeshop.py
stromer_api/bikestate.py
stromer_api/bikestatistics.py
stromer_api/bikeuser.py
stromer_api/daystats.py
stromer_api/general.py
stromer_api/monthstats.py
stromer_api/periodicinfo.py
stromer_api/periodstats.py
stromer_api/portal.py
stromer_api/service_info.py
stromer_api/service_log.py
stromer_api/weekstats.py
stromer_api/yearstats.py
stromer_api.egg-info/PKG-INFO
stromer_api.egg-info/SOURCES.txt
stromer_api.egg-info/dependency_links.txt
stromer_api.egg-info/top_level.txt