Metadata-Version: 2.1
Name: stromer-api
Version: 2.0.4
Summary: Stromer API for accessing data from your Stromer Speed Bike.
Home-page: https://github.com/elnkosc/stromer_api
Author: Koen
Author-email: koen@schilders.org
License: GPL
Keywords: Stromer,EBike,Python,API
